calitp/__init__.py
calitp/config.py
calitp/storage.py
calitp/templates.py
calitp-2023.2.10.dist-info/WHEEL
calitp-2023.2.10.dist-info/METADATA
calitp-2023.2.10.dist-info/RECORD
